Metadata-Version: 2.1
Name: nonebot-plugin-multigpt
Version: 3.4
Summary: a python package for multiGPT,多模态ai工具
Author: syagina
Author-email: 3173707804@qq.com
Keywords: python,GPT,ppt,word,docx,image,ai,multi
Classifier: Development Status :: 1 - Planning
Classifier: Intended Audience :: Developers
Classifier: Programming Language :: Python :: 3
Classifier: Operating System :: Unix
Classifier: Operating System :: MacOS :: MacOS X
Classifier: Operating System :: Microsoft :: Windows
License-File: LICENSE
